{
	"entries" : 
	[
		{
			"name" : "APPLICATION_HELP_URL",
			"properties" : 
			[
				{
					"name" : "HELPSTRING",
					"value" : "URL for the help menu"
				}
			],
			"type" : "STRING",
			"value" : ""
		},
		{
			"name" : "APPLICATION_SERVER_URL",
			"properties" : 
			[
				{
					"name" : "HELPSTRING",
					"value" : "URL for the server to use. If entered, the UI field will be pre-filled with it"
				}
			],
			"type" : "STRING",
			"value" : ""
		},
		{
			"name" : "APPLICATION_UPDATE_URL",
			"properties" : 
			[
				{
					"name" : "HELPSTRING",
					"value" : "URL for updater"
				}
			],
			"type" : "STRING",
			"value" : "https://updates.nextcloud.org/client/"
		},
		{
			"name" : "APPLICATION_VIRTUALFILE_SUFFIX",
			"properties" : 
			[
				{
					"name" : "HELPSTRING",
					"value" : "Virtual file suffix (not including the .)"
				}
			],
			"type" : "STRING",
			"value" : "nextcloud"
		},
		{
			"name" : "APPLICATION_WIZARD_HEADER_BACKGROUND_COLOR",
			"properties" : 
			[
				{
					"name" : "HELPSTRING",
					"value" : "Hex color of the wizard header background"
				}
			],
			"type" : "STRING",
			"value" : "#0082c9"
		},
		{
			"name" : "APPLICATION_WIZARD_HEADER_TITLE_COLOR",
			"properties" : 
			[
				{
					"name" : "HELPSTRING",
					"value" : "Hex color of the text in the wizard header"
				}
			],
			"type" : "STRING",
			"value" : "#ffffff"
		},
		{
			"name" : "APPLICATION_WIZARD_USE_CUSTOM_LOGO",
			"properties" : 
			[
				{
					"name" : "HELPSTRING",
					"value" : "Use the logo from ':/client/theme/colored/wizard_logo.(png|svg)' else the default application icon is used"
				}
			],
			"type" : "BOOL",
			"value" : "ON"
		},
		{
			"name" : "BIN_INSTALL_DIR",
			"properties" : 
			[
				{
					"name" : "HELPSTRING",
					"value" : "-"
				}
			],
			"type" : "PATH",
			"value" : "."
		},
		{
			"name" : "BUILD_CLIENT",
			"properties" : 
			[
				{
					"name" : "HELPSTRING",
					"value" : "BUILD_CLIENT"
				}
			],
			"type" : "BOOL",
			"value" : "ON"
		},
		{
			"name" : "BUILD_COVERAGE",
			"properties" : 
			[
				{
					"name" : "HELPSTRING",
					"value" : "Build the project with gcov support"
				}
			],
			"type" : "BOOL",
			"value" : "OFF"
		},
		{
			"name" : "BUILD_GUI",
			"properties" : 
			[
				{
					"name" : "HELPSTRING",
					"value" : "BUILD_GUI"
				}
			],
			"type" : "BOOL",
			"value" : "ON"
		},
		{
			"name" : "BUILD_LIBRARIES_ONLY",
			"properties" : 
			[
				{
					"name" : "HELPSTRING",
					"value" : "BUILD_LIBRARIES_ONLY"
				}
			],
			"type" : "BOOL",
			"value" : "OFF"
		},
		{
			"name" : "BUILD_SHELL_INTEGRATION",
			"properties" : 
			[
				{
					"name" : "HELPSTRING",
					"value" : "BUILD_SHELL_INTEGRATION"
				}
			],
			"type" : "BOOL",
			"value" : "ON"
		},
		{
			"name" : "BUILD_SHELL_INTEGRATION_DOLPHIN",
			"properties" : 
			[
				{
					"name" : "HELPSTRING",
					"value" : "BUILD_SHELL_INTEGRATION_DOLPHIN"
				}
			],
			"type" : "BOOL",
			"value" : "ON"
		},
		{
			"name" : "BUILD_SHELL_INTEGRATION_ICONS",
			"properties" : 
			[
				{
					"name" : "HELPSTRING",
					"value" : "BUILD_SHELL_INTEGRATION_ICONS"
				}
			],
			"type" : "BOOL",
			"value" : "ON"
		},
		{
			"name" : "BUILD_SHELL_INTEGRATION_NAUTILUS",
			"properties" : 
			[
				{
					"name" : "HELPSTRING",
					"value" : "BUILD_SHELL_INTEGRATION_NAUTILUS"
				}
			],
			"type" : "BOOL",
			"value" : "ON"
		},
		{
			"name" : "BUILD_TESTING",
			"properties" : 
			[
				{
					"name" : "HELPSTRING",
					"value" : "Build the testing tree."
				}
			],
			"type" : "BOOL",
			"value" : "ON"
		},
		{
			"name" : "BUILD_UPDATER",
			"properties" : 
			[
				{
					"name" : "HELPSTRING",
					"value" : "Build updater"
				}
			],
			"type" : "BOOL",
			"value" : "ON"
		},
		{
			"name" : "BUILD_WIN_MSI",
			"properties" : 
			[
				{
					"name" : "HELPSTRING",
					"value" : "Build MSI scripts and helper DLL"
				}
			],
			"type" : "BOOL",
			"value" : "1"
		},
		{
			"name" : "BUILD_WIN_TOOLS",
			"properties" : 
			[
				{
					"name" : "HELPSTRING",
					"value" : "Build Win32 migration tools"
				}
			],
			"type" : "BOOL",
			"value" : "OFF"
		},
		{
			"name" : "BZRCOMMAND",
			"properties" : 
			[
				{
					"name" : "ADVANCED",
					"value" : "1"
				},
				{
					"name" : "HELPSTRING",
					"value" : "(This variable does not exist and should not be used)"
				}
			],
			"type" : "UNINITIALIZED",
			"value" : ""
		},
		{
			"name" : "CLANG_TIDY_EXE",
			"properties" : 
			[
				{
					"name" : "HELPSTRING",
					"value" : "Path to a program."
				}
			],
			"type" : "FILEPATH",
			"value" : "CLANG_TIDY_EXE-NOTFOUND"
		},
		{
			"name" : "CMAKE_AR",
			"properties" : 
			[
				{
					"name" : "ADVANCED",
					"value" : "1"
				},
				{
					"name" : "HELPSTRING",
					"value" : "Path to a program."
				}
			],
			"type" : "FILEPATH",
			"value" : "C:/Program Files (x86)/Microsoft Visual Studio/2019/Professional/VC/Tools/MSVC/14.29.30133/bin/Hostx64/x64/lib.exe"
		},
		{
			"name" : "CMAKE_BUILD_TYPE",
			"properties" : 
			[
				{
					"name" : "HELPSTRING",
					"value" : "No help, variable specified on the command line."
				}
			],
			"type" : "UNINITIALIZED",
			"value" : "Release"
		},
		{
			"name" : "CMAKE_CACHEFILE_DIR",
			"properties" : 
			[
				{
					"name" : "HELPSTRING",
					"value" : "This is the directory where this CMakeCache.txt was created"
				}
			],
			"type" : "INTERNAL",
			"value" : "c:/NextCloud/client-building/desktop/build"
		},
		{
			"name" : "CMAKE_CACHE_MAJOR_VERSION",
			"properties" : 
			[
				{
					"name" : "HELPSTRING",
					"value" : "Major version of cmake used to create the current loaded cache"
				}
			],
			"type" : "INTERNAL",
			"value" : "3"
		},
		{
			"name" : "CMAKE_CACHE_MINOR_VERSION",
			"properties" : 
			[
				{
					"name" : "HELPSTRING",
					"value" : "Minor version of cmake used to create the current loaded cache"
				}
			],
			"type" : "INTERNAL",
			"value" : "21"
		},
		{
			"name" : "CMAKE_CACHE_PATCH_VERSION",
			"properties" : 
			[
				{
					"name" : "HELPSTRING",
					"value" : "Patch version of cmake used to create the current loaded cache"
				}
			],
			"type" : "INTERNAL",
			"value" : "0"
		},
		{
			"name" : "CMAKE_COMMAND",
			"properties" : 
			[
				{
					"name" : "HELPSTRING",
					"value" : "Path to CMake executable."
				}
			],
			"type" : "INTERNAL",
			"value" : "C:/NextCloud/tools/cmake/bin/cmake.exe"
		},
		{
			"name" : "CMAKE_CONFIGURATION_TYPES",
			"properties" : 
			[
				{
					"name" : "HELPSTRING",
					"value" : "Semicolon separated list of supported configuration types, only supports Debug, Release, MinSizeRel, and RelWithDebInfo, anything else will be ignored."
				}
			],
			"type" : "STRING",
			"value" : "Debug;Release;MinSizeRel;RelWithDebInfo"
		},
		{
			"name" : "CMAKE_CPACK_COMMAND",
			"properties" : 
			[
				{
					"name" : "HELPSTRING",
					"value" : "Path to cpack program executable."
				}
			],
			"type" : "INTERNAL",
			"value" : "C:/NextCloud/tools/cmake/bin/cpack.exe"
		},
		{
			"name" : "CMAKE_CTEST_COMMAND",
			"properties" : 
			[
				{
					"name" : "ADVANCED",
					"value" : "1"
				},
				{
					"name" : "HELPSTRING",
					"value" : "Path to ctest program executable."
				}
			],
			"type" : "INTERNAL",
			"value" : "C:/NextCloud/tools/cmake/bin/ctest.exe"
		},
		{
			"name" : "CMAKE_CXX_COMPILER",
			"properties" : 
			[
				{
					"name" : "HELPSTRING",
					"value" : "No help, variable specified on the command line."
				}
			],
			"type" : "STRING",
			"value" : "C:/Program Files (x86)/Microsoft Visual Studio/2019/Professional/VC/Tools/MSVC/14.29.30133/bin/HostX64/x64/cl.exe"
		},
		{
			"name" : "CMAKE_CXX_FLAGS",
			"properties" : 
			[
				{
					"name" : "ADVANCED",
					"value" : "1"
				},
				{
					"name" : "HELPSTRING",
					"value" : "Flags used by the CXX compiler during all build types."
				}
			],
			"type" : "STRING",
			"value" : "/DWIN32 /D_WINDOWS /GR /EHsc"
		},
		{
			"name" : "CMAKE_CXX_FLAGS_DEBUG",
			"properties" : 
			[
				{
					"name" : "ADVANCED",
					"value" : "1"
				},
				{
					"name" : "HELPSTRING",
					"value" : "Flags used by the CXX compiler during DEBUG builds."
				}
			],
			"type" : "STRING",
			"value" : "/Zi /Ob0 /Od /RTC1"
		},
		{
			"name" : "CMAKE_CXX_FLAGS_MINSIZEREL",
			"properties" : 
			[
				{
					"name" : "ADVANCED",
					"value" : "1"
				},
				{
					"name" : "HELPSTRING",
					"value" : "Flags used by the CXX compiler during MINSIZEREL builds."
				}
			],
			"type" : "STRING",
			"value" : "/O1 /Ob1 /DNDEBUG"
		},
		{
			"name" : "CMAKE_CXX_FLAGS_RELEASE",
			"properties" : 
			[
				{
					"name" : "ADVANCED",
					"value" : "1"
				},
				{
					"name" : "HELPSTRING",
					"value" : "Flags used by the CXX compiler during RELEASE builds."
				}
			],
			"type" : "STRING",
			"value" : "/O2 /Ob2 /DNDEBUG"
		},
		{
			"name" : "CMAKE_CXX_FLAGS_RELWITHDEBINFO",
			"properties" : 
			[
				{
					"name" : "ADVANCED",
					"value" : "1"
				},
				{
					"name" : "HELPSTRING",
					"value" : "Flags used by the CXX compiler during RELWITHDEBINFO builds."
				}
			],
			"type" : "STRING",
			"value" : "/Zi /O2 /Ob1 /DNDEBUG"
		},
		{
			"name" : "CMAKE_CXX_STANDARD_LIBRARIES",
			"properties" : 
			[
				{
					"name" : "ADVANCED",
					"value" : "1"
				},
				{
					"name" : "HELPSTRING",
					"value" : "Libraries linked by default with all C++ applications."
				}
			],
			"type" : "STRING",
			"value" : "kernel32.lib user32.lib gdi32.lib winspool.lib shell32.lib ole32.lib oleaut32.lib uuid.lib comdlg32.lib advapi32.lib"
		},
		{
			"name" : "CMAKE_C_COMPILER",
			"properties" : 
			[
				{
					"name" : "HELPSTRING",
					"value" : "No help, variable specified on the command line."
				}
			],
			"type" : "STRING",
			"value" : "C:/Program Files (x86)/Microsoft Visual Studio/2019/Professional/VC/Tools/MSVC/14.29.30133/bin/HostX64/x64/cl.exe"
		},
		{
			"name" : "CMAKE_C_FLAGS",
			"properties" : 
			[
				{
					"name" : "ADVANCED",
					"value" : "1"
				},
				{
					"name" : "HELPSTRING",
					"value" : "Flags used by the C compiler during all build types."
				}
			],
			"type" : "STRING",
			"value" : "/DWIN32 /D_WINDOWS"
		},
		{
			"name" : "CMAKE_C_FLAGS_DEBUG",
			"properties" : 
			[
				{
					"name" : "ADVANCED",
					"value" : "1"
				},
				{
					"name" : "HELPSTRING",
					"value" : "Flags used by the C compiler during DEBUG builds."
				}
			],
			"type" : "STRING",
			"value" : "/Zi /Ob0 /Od /RTC1"
		},
		{
			"name" : "CMAKE_C_FLAGS_MINSIZEREL",
			"properties" : 
			[
				{
					"name" : "ADVANCED",
					"value" : "1"
				},
				{
					"name" : "HELPSTRING",
					"value" : "Flags used by the C compiler during MINSIZEREL builds."
				}
			],
			"type" : "STRING",
			"value" : "/O1 /Ob1 /DNDEBUG"
		},
		{
			"name" : "CMAKE_C_FLAGS_RELEASE",
			"properties" : 
			[
				{
					"name" : "ADVANCED",
					"value" : "1"
				},
				{
					"name" : "HELPSTRING",
					"value" : "Flags used by the C compiler during RELEASE builds."
				}
			],
			"type" : "STRING",
			"value" : "/O2 /Ob2 /DNDEBUG"
		},
		{
			"name" : "CMAKE_C_FLAGS_RELWITHDEBINFO",
			"properties" : 
			[
				{
					"name" : "ADVANCED",
					"value" : "1"
				},
				{
					"name" : "HELPSTRING",
					"value" : "Flags used by the C compiler during RELWITHDEBINFO builds."
				}
			],
			"type" : "STRING",
			"value" : "/Zi /O2 /Ob1 /DNDEBUG"
		},
		{
			"name" : "CMAKE_C_STANDARD_LIBRARIES",
			"properties" : 
			[
				{
					"name" : "ADVANCED",
					"value" : "1"
				},
				{
					"name" : "HELPSTRING",
					"value" : "Libraries linked by default with all C applications."
				}
			],
			"type" : "STRING",
			"value" : "kernel32.lib user32.lib gdi32.lib winspool.lib shell32.lib ole32.lib oleaut32.lib uuid.lib comdlg32.lib advapi32.lib"
		},
		{
			"name" : "CMAKE_EXECUTABLE_FORMAT",
			"properties" : 
			[
				{
					"name" : "HELPSTRING",
					"value" : "Executable file format"
				}
			],
			"type" : "INTERNAL",
			"value" : "Unknown"
		},
		{
			"name" : "CMAKE_EXE_LINKER_FLAGS",
			"properties" : 
			[
				{
					"name" : "ADVANCED",
					"value" : "1"
				},
				{
					"name" : "HELPSTRING",
					"value" : "Flags used by the linker during all build types."
				}
			],
			"type" : "STRING",
			"value" : "/machine:x64"
		},
		{
			"name" : "CMAKE_EXE_LINKER_FLAGS_DEBUG",
			"properties" : 
			[
				{
					"name" : "ADVANCED",
					"value" : "1"
				},
				{
					"name" : "HELPSTRING",
					"value" : "Flags used by the linker during DEBUG builds."
				}
			],
			"type" : "STRING",
			"value" : "/debug /INCREMENTAL"
		},
		{
			"name" : "CMAKE_EXE_LINKER_FLAGS_MINSIZEREL",
			"properties" : 
			[
				{
					"name" : "ADVANCED",
					"value" : "1"
				},
				{
					"name" : "HELPSTRING",
					"value" : "Flags used by the linker during MINSIZEREL builds."
				}
			],
			"type" : "STRING",
			"value" : "/INCREMENTAL:NO"
		},
		{
			"name" : "CMAKE_EXE_LINKER_FLAGS_RELEASE",
			"properties" : 
			[
				{
					"name" : "ADVANCED",
					"value" : "1"
				},
				{
					"name" : "HELPSTRING",
					"value" : "Flags used by the linker during RELEASE builds."
				}
			],
			"type" : "STRING",
			"value" : "/INCREMENTAL:NO"
		},
		{
			"name" : "CMAKE_EXE_LINKER_FLAGS_RELWITHDEBINFO",
			"properties" : 
			[
				{
					"name" : "ADVANCED",
					"value" : "1"
				},
				{
					"name" : "HELPSTRING",
					"value" : "Flags used by the linker during RELWITHDEBINFO builds."
				}
			],
			"type" : "STRING",
			"value" : "/debug /INCREMENTAL"
		},
		{
			"name" : "CMAKE_EXTRA_GENERATOR",
			"properties" : 
			[
				{
					"name" : "HELPSTRING",
					"value" : "Name of external makefile project generator."
				}
			],
			"type" : "INTERNAL",
			"value" : ""
		},
		{
			"name" : "CMAKE_GENERATOR",
			"properties" : 
			[
				{
					"name" : "HELPSTRING",
					"value" : "Name of generator."
				}
			],
			"type" : "INTERNAL",
			"value" : "Visual Studio 16 2019"
		},
		{
			"name" : "CMAKE_GENERATOR_INSTANCE",
			"properties" : 
			[
				{
					"name" : "HELPSTRING",
					"value" : "Generator instance identifier."
				}
			],
			"type" : "INTERNAL",
			"value" : "C:/Program Files (x86)/Microsoft Visual Studio/2019/Professional"
		},
		{
			"name" : "CMAKE_GENERATOR_PLATFORM",
			"properties" : 
			[
				{
					"name" : "HELPSTRING",
					"value" : "No help, variable specified on the command line."
				}
			],
			"type" : "UNINITIALIZED",
			"value" : "x64"
		},
		{
			"name" : "CMAKE_GENERATOR_TOOLSET",
			"properties" : 
			[
				{
					"name" : "HELPSTRING",
					"value" : "Name of generator toolset."
				}
			],
			"type" : "INTERNAL",
			"value" : ""
		},
		{
			"name" : "CMAKE_HOME_DIRECTORY",
			"properties" : 
			[
				{
					"name" : "HELPSTRING",
					"value" : "Source directory with the top level CMakeLists.txt file for this project"
				}
			],
			"type" : "INTERNAL",
			"value" : "C:/NextCloud/client-building/desktop"
		},
		{
			"name" : "CMAKE_INSTALL_BINDIR",
			"properties" : 
			[
				{
					"name" : "ADVANCED",
					"value" : "1"
				},
				{
					"name" : "HELPSTRING",
					"value" : "User executables (bin)"
				}
			],
			"type" : "PATH",
			"value" : "bin"
		},
		{
			"name" : "CMAKE_INSTALL_DATADIR",
			"properties" : 
			[
				{
					"name" : "ADVANCED",
					"value" : "1"
				},
				{
					"name" : "HELPSTRING",
					"value" : "Read-only architecture-independent data (DATAROOTDIR)"
				}
			],
			"type" : "PATH",
			"value" : ""
		},
		{
			"name" : "CMAKE_INSTALL_DATAROOTDIR",
			"properties" : 
			[
				{
					"name" : "ADVANCED",
					"value" : "1"
				},
				{
					"name" : "HELPSTRING",
					"value" : "Read-only architecture-independent data root (share)"
				}
			],
			"type" : "PATH",
			"value" : "share"
		},
		{
			"name" : "CMAKE_INSTALL_DOCDIR",
			"properties" : 
			[
				{
					"name" : "ADVANCED",
					"value" : "1"
				},
				{
					"name" : "HELPSTRING",
					"value" : "Documentation root (DATAROOTDIR/doc/PROJECT_NAME)"
				}
			],
			"type" : "PATH",
			"value" : ""
		},
		{
			"name" : "CMAKE_INSTALL_INCLUDEDIR",
			"properties" : 
			[
				{
					"name" : "ADVANCED",
					"value" : "1"
				},
				{
					"name" : "HELPSTRING",
					"value" : "C header files (include)"
				}
			],
			"type" : "PATH",
			"value" : "include"
		},
		{
			"name" : "CMAKE_INSTALL_INFODIR",
			"properties" : 
			[
				{
					"name" : "ADVANCED",
					"value" : "1"
				},
				{
					"name" : "HELPSTRING",
					"value" : "Info documentation (DATAROOTDIR/info)"
				}
			],
			"type" : "PATH",
			"value" : ""
		},
		{
			"name" : "CMAKE_INSTALL_LIBDIR",
			"properties" : 
			[
				{
					"name" : "ADVANCED",
					"value" : "1"
				},
				{
					"name" : "HELPSTRING",
					"value" : "Object code libraries (lib)"
				}
			],
			"type" : "PATH",
			"value" : "lib"
		},
		{
			"name" : "CMAKE_INSTALL_LIBEXECDIR",
			"properties" : 
			[
				{
					"name" : "ADVANCED",
					"value" : "1"
				},
				{
					"name" : "HELPSTRING",
					"value" : "Program executables (libexec)"
				}
			],
			"type" : "PATH",
			"value" : "libexec"
		},
		{
			"name" : "CMAKE_INSTALL_LOCALEDIR",
			"properties" : 
			[
				{
					"name" : "ADVANCED",
					"value" : "1"
				},
				{
					"name" : "HELPSTRING",
					"value" : "Locale-dependent data (DATAROOTDIR/locale)"
				}
			],
			"type" : "PATH",
			"value" : ""
		},
		{
			"name" : "CMAKE_INSTALL_LOCALSTATEDIR",
			"properties" : 
			[
				{
					"name" : "ADVANCED",
					"value" : "1"
				},
				{
					"name" : "HELPSTRING",
					"value" : "Modifiable single-machine data (var)"
				}
			],
			"type" : "PATH",
			"value" : "var"
		},
		{
			"name" : "CMAKE_INSTALL_MANDIR",
			"properties" : 
			[
				{
					"name" : "ADVANCED",
					"value" : "1"
				},
				{
					"name" : "HELPSTRING",
					"value" : "Man documentation (DATAROOTDIR/man)"
				}
			],
			"type" : "PATH",
			"value" : ""
		},
		{
			"name" : "CMAKE_INSTALL_OLDINCLUDEDIR",
			"properties" : 
			[
				{
					"name" : "ADVANCED",
					"value" : "1"
				},
				{
					"name" : "HELPSTRING",
					"value" : "C header files for non-gcc (/usr/include)"
				}
			],
			"type" : "PATH",
			"value" : "/usr/include"
		},
		{
			"name" : "CMAKE_INSTALL_PREFIX",
			"properties" : 
			[
				{
					"name" : "HELPSTRING",
					"value" : "Install path prefix, prepended onto install directories."
				}
			],
			"type" : "PATH",
			"value" : "C:/NextCloud/client-building/install/Release/Win64"
		},
		{
			"name" : "CMAKE_INSTALL_RUNSTATEDIR",
			"properties" : 
			[
				{
					"name" : "ADVANCED",
					"value" : "1"
				},
				{
					"name" : "HELPSTRING",
					"value" : "Run-time variable data (LOCALSTATEDIR/run)"
				}
			],
			"type" : "PATH",
			"value" : ""
		},
		{
			"name" : "CMAKE_INSTALL_SBINDIR",
			"properties" : 
			[
				{
					"name" : "ADVANCED",
					"value" : "1"
				},
				{
					"name" : "HELPSTRING",
					"value" : "System admin executables (sbin)"
				}
			],
			"type" : "PATH",
			"value" : "sbin"
		},
		{
			"name" : "CMAKE_INSTALL_SHAREDSTATEDIR",
			"properties" : 
			[
				{
					"name" : "ADVANCED",
					"value" : "1"
				},
				{
					"name" : "HELPSTRING",
					"value" : "Modifiable architecture-independent data (com)"
				}
			],
			"type" : "PATH",
			"value" : "com"
		},
		{
			"name" : "CMAKE_INSTALL_SYSCONFDIR",
			"properties" : 
			[
				{
					"name" : "ADVANCED",
					"value" : "1"
				},
				{
					"name" : "HELPSTRING",
					"value" : "Read-only single-machine data (etc)"
				}
			],
			"type" : "PATH",
			"value" : "etc"
		},
		{
			"name" : "CMAKE_LINKER",
			"properties" : 
			[
				{
					"name" : "ADVANCED",
					"value" : "1"
				},
				{
					"name" : "HELPSTRING",
					"value" : "Path to a program."
				}
			],
			"type" : "FILEPATH",
			"value" : "C:/Program Files (x86)/Microsoft Visual Studio/2019/Professional/VC/Tools/MSVC/14.29.30133/bin/Hostx64/x64/link.exe"
		},
		{
			"name" : "CMAKE_MODULE_LINKER_FLAGS",
			"properties" : 
			[
				{
					"name" : "ADVANCED",
					"value" : "1"
				},
				{
					"name" : "HELPSTRING",
					"value" : "Flags used by the linker during the creation of modules during all build types."
				}
			],
			"type" : "STRING",
			"value" : "/machine:x64"
		},
		{
			"name" : "CMAKE_MODULE_LINKER_FLAGS_DEBUG",
			"properties" : 
			[
				{
					"name" : "ADVANCED",
					"value" : "1"
				},
				{
					"name" : "HELPSTRING",
					"value" : "Flags used by the linker during the creation of modules during DEBUG builds."
				}
			],
			"type" : "STRING",
			"value" : "/debug /INCREMENTAL"
		},
		{
			"name" : "CMAKE_MODULE_LINKER_FLAGS_MINSIZEREL",
			"properties" : 
			[
				{
					"name" : "ADVANCED",
					"value" : "1"
				},
				{
					"name" : "HELPSTRING",
					"value" : "Flags used by the linker during the creation of modules during MINSIZEREL builds."
				}
			],
			"type" : "STRING",
			"value" : "/INCREMENTAL:NO"
		},
		{
			"name" : "CMAKE_MODULE_LINKER_FLAGS_RELEASE",
			"properties" : 
			[
				{
					"name" : "ADVANCED",
					"value" : "1"
				},
				{
					"name" : "HELPSTRING",
					"value" : "Flags used by the linker during the creation of modules during RELEASE builds."
				}
			],
			"type" : "STRING",
			"value" : "/INCREMENTAL:NO"
		},
		{
			"name" : "CMAKE_MODULE_LINKER_FLAGS_RELWITHDEBINFO",
			"properties" : 
			[
				{
					"name" : "ADVANCED",
					"value" : "1"
				},
				{
					"name" : "HELPSTRING",
					"value" : "Flags used by the linker during the creation of modules during RELWITHDEBINFO builds."
				}
			],
			"type" : "STRING",
			"value" : "/debug /INCREMENTAL"
		},
		{
			"name" : "CMAKE_MT",
			"properties" : 
			[
				{
					"name" : "ADVANCED",
					"value" : "1"
				},
				{
					"name" : "HELPSTRING",
					"value" : "Path to a program."
				}
			],
			"type" : "FILEPATH",
			"value" : "C:/Program Files (x86)/Windows Kits/10/bin/10.0.19041.0/x64/mt.exe"
		},
		{
			"name" : "CMAKE_NUMBER_OF_MAKEFILES",
			"properties" : 
			[
				{
					"name" : "HELPSTRING",
					"value" : "number of local generators"
				}
			],
			"type" : "INTERNAL",
			"value" : "29"
		},
		{
			"name" : "CMAKE_PLATFORM_INFO_INITIALIZED",
			"properties" : 
			[
				{
					"name" : "HELPSTRING",
					"value" : "Platform information initialized"
				}
			],
			"type" : "INTERNAL",
			"value" : "1"
		},
		{
			"name" : "CMAKE_PREFIX_PATH",
			"properties" : 
			[
				{
					"name" : "HELPSTRING",
					"value" : "No help, variable specified on the command line."
				}
			],
			"type" : "UNINITIALIZED",
			"value" : "c:/Qt/5.15.8\\msvc2019_64;c:/Nextcloud/client-building\\QtKeychain"
		},
		{
			"name" : "CMAKE_PROJECT_DESCRIPTION",
			"properties" : 
			[
				{
					"name" : "HELPSTRING",
					"value" : "Value Computed by CMake"
				}
			],
			"type" : "STATIC",
			"value" : ""
		},
		{
			"name" : "CMAKE_PROJECT_HOMEPAGE_URL",
			"properties" : 
			[
				{
					"name" : "HELPSTRING",
					"value" : "Value Computed by CMake"
				}
			],
			"type" : "STATIC",
			"value" : ""
		},
		{
			"name" : "CMAKE_PROJECT_INCLUDE_BEFORE",
			"properties" : 
			[
				{
					"name" : "HELPSTRING",
					"value" : "No help, variable specified on the command line."
				}
			],
			"type" : "PATH",
			"value" : "C:/Qt/Tools/QtCreator/share/qtcreator/package-manager/auto-setup.cmake"
		},
		{
			"name" : "CMAKE_PROJECT_NAME",
			"properties" : 
			[
				{
					"name" : "HELPSTRING",
					"value" : "Value Computed by CMake"
				}
			],
			"type" : "STATIC",
			"value" : "client"
		},
		{
			"name" : "CMAKE_RANLIB",
			"properties" : 
			[
				{
					"name" : "HELPSTRING",
					"value" : "noop for ranlib"
				}
			],
			"type" : "INTERNAL",
			"value" : ":"
		},
		{
			"name" : "CMAKE_RC_COMPILER",
			"properties" : 
			[
				{
					"name" : "ADVANCED",
					"value" : "1"
				},
				{
					"name" : "HELPSTRING",
					"value" : "RC compiler"
				}
			],
			"type" : "FILEPATH",
			"value" : "C:/Program Files (x86)/Windows Kits/10/bin/10.0.19041.0/x64/rc.exe"
		},
		{
			"name" : "CMAKE_RC_COMPILER_WORKS",
			"properties" : 
			[
				{
					"name" : "HELPSTRING",
					"value" : ""
				}
			],
			"type" : "INTERNAL",
			"value" : "1"
		},
		{
			"name" : "CMAKE_RC_FLAGS",
			"properties" : 
			[
				{
					"name" : "ADVANCED",
					"value" : "1"
				},
				{
					"name" : "HELPSTRING",
					"value" : "Flags for Windows Resource Compiler during all build types."
				}
			],
			"type" : "STRING",
			"value" : "-DWIN32"
		},
		{
			"name" : "CMAKE_RC_FLAGS_DEBUG",
			"properties" : 
			[
				{
					"name" : "ADVANCED",
					"value" : "1"
				},
				{
					"name" : "HELPSTRING",
					"value" : "Flags for Windows Resource Compiler during DEBUG builds."
				}
			],
			"type" : "STRING",
			"value" : "-D_DEBUG"
		},
		{
			"name" : "CMAKE_RC_FLAGS_MINSIZEREL",
			"properties" : 
			[
				{
					"name" : "ADVANCED",
					"value" : "1"
				},
				{
					"name" : "HELPSTRING",
					"value" : "Flags for Windows Resource Compiler during MINSIZEREL builds."
				}
			],
			"type" : "STRING",
			"value" : ""
		},
		{
			"name" : "CMAKE_RC_FLAGS_RELEASE",
			"properties" : 
			[
				{
					"name" : "ADVANCED",
					"value" : "1"
				},
				{
					"name" : "HELPSTRING",
					"value" : "Flags for Windows Resource Compiler during RELEASE builds."
				}
			],
			"type" : "STRING",
			"value" : ""
		},
		{
			"name" : "CMAKE_RC_FLAGS_RELWITHDEBINFO",
			"properties" : 
			[
				{
					"name" : "ADVANCED",
					"value" : "1"
				},
				{
					"name" : "HELPSTRING",
					"value" : "Flags for Windows Resource Compiler during RELWITHDEBINFO builds."
				}
			],
			"type" : "STRING",
			"value" : ""
		},
		{
			"name" : "CMAKE_ROOT",
			"properties" : 
			[
				{
					"name" : "HELPSTRING",
					"value" : "Path to CMake installation."
				}
			],
			"type" : "INTERNAL",
			"value" : "C:/NextCloud/tools/cmake/share/cmake-3.21"
		},
		{
			"name" : "CMAKE_SHARED_LINKER_FLAGS",
			"properties" : 
			[
				{
					"name" : "ADVANCED",
					"value" : "1"
				},
				{
					"name" : "HELPSTRING",
					"value" : "Flags used by the linker during the creation of shared libraries during all build types."
				}
			],
			"type" : "STRING",
			"value" : "/machine:x64"
		},
		{
			"name" : "CMAKE_SHARED_LINKER_FLAGS_DEBUG",
			"properties" : 
			[
				{
					"name" : "ADVANCED",
					"value" : "1"
				},
				{
					"name" : "HELPSTRING",
					"value" : "Flags used by the linker during the creation of shared libraries during DEBUG builds."
				}
			],
			"type" : "STRING",
			"value" : "/debug /INCREMENTAL"
		},
		{
			"name" : "CMAKE_SHARED_LINKER_FLAGS_MINSIZEREL",
			"properties" : 
			[
				{
					"name" : "ADVANCED",
					"value" : "1"
				},
				{
					"name" : "HELPSTRING",
					"value" : "Flags used by the linker during the creation of shared libraries during MINSIZEREL builds."
				}
			],
			"type" : "STRING",
			"value" : "/INCREMENTAL:NO"
		},
		{
			"name" : "CMAKE_SHARED_LINKER_FLAGS_RELEASE",
			"properties" : 
			[
				{
					"name" : "ADVANCED",
					"value" : "1"
				},
				{
					"name" : "HELPSTRING",
					"value" : "Flags used by the linker during the creation of shared libraries during RELEASE builds."
				}
			],
			"type" : "STRING",
			"value" : "/INCREMENTAL:NO"
		},
		{
			"name" : "CMAKE_SHARED_LINKER_FLAGS_RELWITHDEBINFO",
			"properties" : 
			[
				{
					"name" : "ADVANCED",
					"value" : "1"
				},
				{
					"name" : "HELPSTRING",
					"value" : "Flags used by the linker during the creation of shared libraries during RELWITHDEBINFO builds."
				}
			],
			"type" : "STRING",
			"value" : "/debug /INCREMENTAL"
		},
		{
			"name" : "CMAKE_SKIP_INSTALL_RPATH",
			"properties" : 
			[
				{
					"name" : "ADVANCED",
					"value" : "1"
				},
				{
					"name" : "HELPSTRING",
					"value" : "If set, runtime paths are not added when installing shared libraries, but are added when building."
				}
			],
			"type" : "BOOL",
			"value" : "NO"
		},
		{
			"name" : "CMAKE_SKIP_RPATH",
			"properties" : 
			[
				{
					"name" : "ADVANCED",
					"value" : "1"
				},
				{
					"name" : "HELPSTRING",
					"value" : "If set, runtime paths are not added when using shared libraries."
				}
			],
			"type" : "BOOL",
			"value" : "NO"
		},
		{
			"name" : "CMAKE_STATIC_LINKER_FLAGS",
			"properties" : 
			[
				{
					"name" : "ADVANCED",
					"value" : "1"
				},
				{
					"name" : "HELPSTRING",
					"value" : "Flags used by the linker during the creation of static libraries during all build types."
				}
			],
			"type" : "STRING",
			"value" : "/machine:x64"
		},
		{
			"name" : "CMAKE_STATIC_LINKER_FLAGS_DEBUG",
			"properties" : 
			[
				{
					"name" : "ADVANCED",
					"value" : "1"
				},
				{
					"name" : "HELPSTRING",
					"value" : "Flags used by the linker during the creation of static libraries during DEBUG builds."
				}
			],
			"type" : "STRING",
			"value" : ""
		},
		{
			"name" : "CMAKE_STATIC_LINKER_FLAGS_MINSIZEREL",
			"properties" : 
			[
				{
					"name" : "ADVANCED",
					"value" : "1"
				},
				{
					"name" : "HELPSTRING",
					"value" : "Flags used by the linker during the creation of static libraries during MINSIZEREL builds."
				}
			],
			"type" : "STRING",
			"value" : ""
		},
		{
			"name" : "CMAKE_STATIC_LINKER_FLAGS_RELEASE",
			"properties" : 
			[
				{
					"name" : "ADVANCED",
					"value" : "1"
				},
				{
					"name" : "HELPSTRING",
					"value" : "Flags used by the linker during the creation of static libraries during RELEASE builds."
				}
			],
			"type" : "STRING",
			"value" : ""
		},
		{
			"name" : "CMAKE_STATIC_LINKER_FLAGS_RELWITHDEBINFO",
			"properties" : 
			[
				{
					"name" : "ADVANCED",
					"value" : "1"
				},
				{
					"name" : "HELPSTRING",
					"value" : "Flags used by the linker during the creation of static libraries during RELWITHDEBINFO builds."
				}
			],
			"type" : "STRING",
			"value" : ""
		},
		{
			"name" : "CMAKE_VERBOSE_MAKEFILE",
			"properties" : 
			[
				{
					"name" : "ADVANCED",
					"value" : "1"
				},
				{
					"name" : "HELPSTRING",
					"value" : "If this value is on, makefiles will be generated without the .SILENT directive, and all commands will be echoed to the console during the make.  This is useful for debugging only. With Visual Studio IDE projects all commands are done without /nologo."
				}
			],
			"type" : "BOOL",
			"value" : "FALSE"
		},
		{
			"name" : "CMOCKA_INCLUDE_DIR",
			"properties" : 
			[
				{
					"name" : "ADVANCED",
					"value" : "1"
				},
				{
					"name" : "HELPSTRING",
					"value" : "Path to a file."
				}
			],
			"type" : "PATH",
			"value" : "CMOCKA_INCLUDE_DIR-NOTFOUND"
		},
		{
			"name" : "CMOCKA_LIBRARIES",
			"properties" : 
			[
				{
					"name" : "ADVANCED",
					"value" : "1"
				},
				{
					"name" : "HELPSTRING",
					"value" : "(This variable does not exist and should not be used)"
				}
			],
			"type" : "UNINITIALIZED",
			"value" : ""
		},
		{
			"name" : "CMOCKA_LIBRARY",
			"properties" : 
			[
				{
					"name" : "HELPSTRING",
					"value" : "Path to a library."
				}
			],
			"type" : "FILEPATH",
			"value" : "CMOCKA_LIBRARY-NOTFOUND"
		},
		{
			"name" : "COMPILER_HAS_DEPRECATED",
			"properties" : 
			[
				{
					"name" : "HELPSTRING",
					"value" : "Test COMPILER_HAS_DEPRECATED"
				}
			],
			"type" : "INTERNAL",
			"value" : "1"
		},
		{
			"name" : "COMPILER_HAS_DEPRECATED_ATTR",
			"properties" : 
			[
				{
					"name" : "HELPSTRING",
					"value" : "Test COMPILER_HAS_DEPRECATED_ATTR"
				}
			],
			"type" : "INTERNAL",
			"value" : ""
		},
		{
			"name" : "COVERAGE_COMMAND",
			"properties" : 
			[
				{
					"name" : "ADVANCED",
					"value" : "1"
				},
				{
					"name" : "HELPSTRING",
					"value" : "Path to the coverage program that CTest uses for performing coverage inspection"
				}
			],
			"type" : "FILEPATH",
			"value" : "C:/Strawberry/c/bin/gcov.exe"
		},
		{
			"name" : "COVERAGE_EXTRA_FLAGS",
			"properties" : 
			[
				{
					"name" : "ADVANCED",
					"value" : "1"
				},
				{
					"name" : "HELPSTRING",
					"value" : "Extra command line flags to pass to the coverage tool"
				}
			],
			"type" : "STRING",
			"value" : "-l"
		},
		{
			"name" : "CPACK_BINARY_7Z",
			"properties" : 
			[
				{
					"name" : "ADVANCED",
					"value" : "1"
				},
				{
					"name" : "HELPSTRING",
					"value" : "Enable to build 7-Zip packages"
				}
			],
			"type" : "BOOL",
			"value" : "OFF"
		},
		{
			"name" : "CPACK_BINARY_IFW",
			"properties" : 
			[
				{
					"name" : "ADVANCED",
					"value" : "1"
				},
				{
					"name" : "HELPSTRING",
					"value" : "Enable to build IFW packages"
				}
			],
			"type" : "BOOL",
			"value" : "OFF"
		},
		{
			"name" : "CPACK_BINARY_NSIS",
			"properties" : 
			[
				{
					"name" : "ADVANCED",
					"value" : "1"
				},
				{
					"name" : "HELPSTRING",
					"value" : "Enable to build NSIS packages"
				}
			],
			"type" : "BOOL",
			"value" : "ON"
		},
		{
			"name" : "CPACK_BINARY_NUGET",
			"properties" : 
			[
				{
					"name" : "ADVANCED",
					"value" : "1"
				},
				{
					"name" : "HELPSTRING",
					"value" : "Enable to build NuGet packages"
				}
			],
			"type" : "BOOL",
			"value" : "OFF"
		},
		{
			"name" : "CPACK_BINARY_WIX",
			"properties" : 
			[
				{
					"name" : "ADVANCED",
					"value" : "1"
				},
				{
					"name" : "HELPSTRING",
					"value" : "Enable to build WiX packages"
				}
			],
			"type" : "BOOL",
			"value" : "OFF"
		},
		{
			"name" : "CPACK_BINARY_ZIP",
			"properties" : 
			[
				{
					"name" : "ADVANCED",
					"value" : "1"
				},
				{
					"name" : "HELPSTRING",
					"value" : "Enable to build ZIP packages"
				}
			],
			"type" : "BOOL",
			"value" : "OFF"
		},
		{
			"name" : "CPACK_SOURCE_7Z",
			"properties" : 
			[
				{
					"name" : "ADVANCED",
					"value" : "1"
				},
				{
					"name" : "HELPSTRING",
					"value" : "Enable to build 7-Zip source packages"
				}
			],
			"type" : "BOOL",
			"value" : "ON"
		},
		{
			"name" : "CPACK_SOURCE_ZIP",
			"properties" : 
			[
				{
					"name" : "ADVANCED",
					"value" : "1"
				},
				{
					"name" : "HELPSTRING",
					"value" : "Enable to build ZIP source packages"
				}
			],
			"type" : "BOOL",
			"value" : "ON"
		},
		{
			"name" : "CSYNC_REQUIRED_LIBRARIES",
			"properties" : 
			[
				{
					"name" : "HELPSTRING",
					"value" : "csync required system libraries"
				}
			],
			"type" : "INTERNAL",
			"value" : "psapi;kernel32"
		},
		{
			"name" : "CTEST_SUBMIT_RETRY_COUNT",
			"properties" : 
			[
				{
					"name" : "ADVANCED",
					"value" : "1"
				},
				{
					"name" : "HELPSTRING",
					"value" : "How many times to retry timed-out CTest submissions."
				}
			],
			"type" : "STRING",
			"value" : "3"
		},
		{
			"name" : "CTEST_SUBMIT_RETRY_DELAY",
			"properties" : 
			[
				{
					"name" : "ADVANCED",
					"value" : "1"
				},
				{
					"name" : "HELPSTRING",
					"value" : "How long to wait between timed-out CTest submissions."
				}
			],
			"type" : "STRING",
			"value" : "5"
		},
		{
			"name" : "CVSCOMMAND",
			"properties" : 
			[
				{
					"name" : "ADVANCED",
					"value" : "1"
				},
				{
					"name" : "HELPSTRING",
					"value" : "(This variable does not exist and should not be used)"
				}
			],
			"type" : "UNINITIALIZED",
			"value" : ""
		},
		{
			"name" : "CVS_UPDATE_OPTIONS",
			"properties" : 
			[
				{
					"name" : "ADVANCED",
					"value" : "1"
				},
				{
					"name" : "HELPSTRING",
					"value" : "(This variable does not exist and should not be used)"
				}
			],
			"type" : "UNINITIALIZED",
			"value" : ""
		},
		{
			"name" : "DART_TESTING_TIMEOUT",
			"properties" : 
			[
				{
					"name" : "ADVANCED",
					"value" : "1"
				},
				{
					"name" : "HELPSTRING",
					"value" : "Maximum time allowed before CTest will kill the test."
				}
			],
			"type" : "STRING",
			"value" : "1500"
		},
		{
			"name" : "DOXYGEN_DOT_EXECUTABLE",
			"properties" : 
			[
				{
					"name" : "ADVANCED",
					"value" : "1"
				},
				{
					"name" : "HELPSTRING",
					"value" : "Dot tool for use with Doxygen"
				}
			],
			"type" : "FILEPATH",
			"value" : "DOXYGEN_DOT_EXECUTABLE-NOTFOUND"
		},
		{
			"name" : "DOXYGEN_EXECUTABLE",
			"properties" : 
			[
				{
					"name" : "ADVANCED",
					"value" : "1"
				},
				{
					"name" : "HELPSTRING",
					"value" : "Doxygen documentation generation tool (http://www.doxygen.org)"
				}
			],
			"type" : "FILEPATH",
			"value" : "C:/Program Files/doxygen/bin/doxygen.exe"
		},
		{
			"name" : "DO_NOT_USE_PROXY",
			"properties" : 
			[
				{
					"name" : "HELPSTRING",
					"value" : "Do not use system wide proxy, instead always do a direct connection to server"
				}
			],
			"type" : "BOOL",
			"value" : "OFF"
		},
		{
			"name" : "ENABLE_CLANG_TIDY",
			"properties" : 
			[
				{
					"name" : "HELPSTRING",
					"value" : "ENABLE_CLANG_TIDY"
				}
			],
			"type" : "BOOL",
			"value" : "OFF"
		},
		{
			"name" : "ENFORCE_VIRTUAL_FILES_SYNC_FOLDER",
			"properties" : 
			[
				{
					"name" : "HELPSTRING",
					"value" : "Enforce use of virtual files sync folder when available"
				}
			],
			"type" : "BOOL",
			"value" : "OFF"
		},
		{
			"name" : "FIND_PACKAGE_MESSAGE_DETAILS_Doxygen",
			"properties" : 
			[
				{
					"name" : "HELPSTRING",
					"value" : "Details about finding Doxygen"
				}
			],
			"type" : "INTERNAL",
			"value" : "[C:/Program Files/doxygen/bin/doxygen.exe][cfound components: doxygen missing components: dot][v1.9.1 (ef9b20ac7f8a8621fcfc299f8bd0b80422390f4b)()]"
		},
		{
			"name" : "FIND_PACKAGE_MESSAGE_DETAILS_OpenSSL",
			"properties" : 
			[
				{
					"name" : "HELPSTRING",
					"value" : "Details about finding OpenSSL"
				}
			],
			"type" : "INTERNAL",
			"value" : "[optimized;C:/OpenSSL/Win64/lib/VC/libcrypto64MD.lib;debug;C:/OpenSSL/Win64/lib/VC/libcrypto64MDd.lib][C:/OpenSSL/Win64/include][c ][v1.1.1l(1.1)]"
		},
		{
			"name" : "FIND_PACKAGE_MESSAGE_DETAILS_Png2Ico",
			"properties" : 
			[
				{
					"name" : "HELPSTRING",
					"value" : "Details about finding Png2Ico"
				}
			],
			"type" : "INTERNAL",
			"value" : "[C:/NextCloud/tools/png2ico.exe][v()]"
		},
		{
			"name" : "FIND_PACKAGE_MESSAGE_DETAILS_ZLIB",
			"properties" : 
			[
				{
					"name" : "HELPSTRING",
					"value" : "Details about finding ZLIB"
				}
			],
			"type" : "INTERNAL",
			"value" : "[c:/Nextcloud/client-building/zlib/build/Release/zlibstatic.lib][C:/NextCloud/client-building/zlib][v1.2.11()]"
		},
		{
			"name" : "GITCOMMAND",
			"properties" : 
			[
				{
					"name" : "ADVANCED",
					"value" : "1"
				},
				{
					"name" : "HELPSTRING",
					"value" : "Path to a program."
				}
			],
			"type" : "FILEPATH",
			"value" : "C:/Program Files/Git/mingw64/bin/git.exe"
		},
		{
			"name" : "GUI_TESTING",
			"properties" : 
			[
				{
					"name" : "HELPSTRING",
					"value" : "Build with gui introspection features of socket api"
				}
			],
			"type" : "BOOL",
			"value" : "OFF"
		},
		{
			"name" : "HAVE_ARGP_H",
			"properties" : 
			[
				{
					"name" : "HELPSTRING",
					"value" : "Have include argp.h"
				}
			],
			"type" : "INTERNAL",
			"value" : ""
		},
		{
			"name" : "HAVE_LIBARGP",
			"properties" : 
			[
				{
					"name" : "HELPSTRING",
					"value" : "Have library argp"
				}
			],
			"type" : "INTERNAL",
			"value" : ""
		},
		{
			"name" : "HAVE_LIBRT",
			"properties" : 
			[
				{
					"name" : "HELPSTRING",
					"value" : "Have library rt"
				}
			],
			"type" : "INTERNAL",
			"value" : ""
		},
		{
			"name" : "HAVE_LSTAT",
			"properties" : 
			[
				{
					"name" : "HELPSTRING",
					"value" : "Have function lstat"
				}
			],
			"type" : "INTERNAL",
			"value" : ""
		},
		{
			"name" : "HAVE_UTIMES",
			"properties" : 
			[
				{
					"name" : "HELPSTRING",
					"value" : "Have function utimes"
				}
			],
			"type" : "INTERNAL",
			"value" : ""
		},
		{
			"name" : "HGCOMMAND",
			"properties" : 
			[
				{
					"name" : "ADVANCED",
					"value" : "1"
				},
				{
					"name" : "HELPSTRING",
					"value" : "(This variable does not exist and should not be used)"
				}
			],
			"type" : "UNINITIALIZED",
			"value" : ""
		},
		{
			"name" : "HTML_INSTALL_DIR",
			"properties" : 
			[
				{
					"name" : "HELPSTRING",
					"value" : "-"
				}
			],
			"type" : "PATH",
			"value" : "doc/HTML"
		},
		{
			"name" : "ICON_INSTALL_DIR",
			"properties" : 
			[
				{
					"name" : "HELPSTRING",
					"value" : "-"
				}
			],
			"type" : "PATH",
			"value" : "."
		},
		{
			"name" : "ICOTOOL_EXECUTABLE",
			"properties" : 
			[
				{
					"name" : "ADVANCED",
					"value" : "1"
				},
				{
					"name" : "HELPSTRING",
					"value" : "Path to a program."
				}
			],
			"type" : "FILEPATH",
			"value" : "ICOTOOL_EXECUTABLE-NOTFOUND"
		},
		{
			"name" : "INCLUDE_INSTALL_DIR",
			"properties" : 
			[
				{
					"name" : "HELPSTRING",
					"value" : "-"
				}
			],
			"type" : "PATH",
			"value" : "include"
		},
		{
			"name" : "KF5Archive_DIR",
			"properties" : 
			[
				{
					"name" : "HELPSTRING",
					"value" : "The directory containing a CMake configuration file for KF5Archive."
				}
			],
			"type" : "PATH",
			"value" : "C:/kderoot/lib/cmake/KF5Archive"
		},
		{
			"name" : "LIB_EAY_DEBUG",
			"properties" : 
			[
				{
					"name" : "HELPSTRING",
					"value" : "Path to a library."
				}
			],
			"type" : "FILEPATH",
			"value" : "C:/OpenSSL/Win64/lib/VC/libcrypto64MDd.lib"
		},
		{
			"name" : "LIB_EAY_LIBRARY_DEBUG",
			"properties" : 
			[
				{
					"name" : "ADVANCED",
					"value" : "1"
				},
				{
					"name" : "HELPSTRING",
					"value" : "(This variable does not exist and should not be used)"
				}
			],
			"type" : "UNINITIALIZED",
			"value" : ""
		},
		{
			"name" : "LIB_EAY_LIBRARY_RELEASE",
			"properties" : 
			[
				{
					"name" : "ADVANCED",
					"value" : "1"
				},
				{
					"name" : "HELPSTRING",
					"value" : "(This variable does not exist and should not be used)"
				}
			],
			"type" : "UNINITIALIZED",
			"value" : ""
		},
		{
			"name" : "LIB_EAY_RELEASE",
			"properties" : 
			[
				{
					"name" : "HELPSTRING",
					"value" : "Path to a library."
				}
			],
			"type" : "FILEPATH",
			"value" : "C:/OpenSSL/Win64/lib/VC/libcrypto64MD.lib"
		},
		{
			"name" : "LIB_INSTALL_DIR",
			"properties" : 
			[
				{
					"name" : "HELPSTRING",
					"value" : "-"
				}
			],
			"type" : "PATH",
			"value" : "lib"
		},
		{
			"name" : "LOCALE_INSTALL_DIR",
			"properties" : 
			[
				{
					"name" : "HELPSTRING",
					"value" : "-"
				}
			],
			"type" : "PATH",
			"value" : "lang"
		},
		{
			"name" : "MAC_INSTALLER_BACKGROUND_FILE",
			"properties" : 
			[
				{
					"name" : "HELPSTRING",
					"value" : "The MacOSX installer background image"
				}
			],
			"type" : "STRING",
			"value" : "C:/NextCloud/client-building/desktop/admin/osx/installer-background.png"
		},
		{
			"name" : "MAKECOMMAND",
			"properties" : 
			[
				{
					"name" : "ADVANCED",
					"value" : "1"
				},
				{
					"name" : "HELPSTRING",
					"value" : "Command to build the project"
				}
			],
			"type" : "STRING",
			"value" : "C:\\NextCloud\\tools\\cmake\\bin\\cmake.exe --build . --config \"${CTEST_CONFIGURATION_TYPE}\""
		},
		{
			"name" : "MAN_INSTALL_DIR",
			"properties" : 
			[
				{
					"name" : "HELPSTRING",
					"value" : "-"
				}
			],
			"type" : "PATH",
			"value" : "man"
		},
		{
			"name" : "MEMORYCHECK_COMMAND",
			"properties" : 
			[
				{
					"name" : "ADVANCED",
					"value" : "1"
				},
				{
					"name" : "HELPSTRING",
					"value" : "Path to the memory checking command, used for memory error detection."
				}
			],
			"type" : "FILEPATH",
			"value" : "MEMORYCHECK_COMMAND-NOTFOUND"
		},
		{
			"name" : "MEMORYCHECK_SUPPRESSIONS_FILE",
			"properties" : 
			[
				{
					"name" : "ADVANCED",
					"value" : "1"
				},
				{
					"name" : "HELPSTRING",
					"value" : "File that contains suppressions for the memory checker"
				}
			],
			"type" : "FILEPATH",
			"value" : ""
		},
		{
			"name" : "MEM_NULL_TESTS",
			"properties" : 
			[
				{
					"name" : "HELPSTRING",
					"value" : "Enable NULL memory testing"
				}
			],
			"type" : "BOOL",
			"value" : "OFF"
		},
		{
			"name" : "MIRALL_VERSION_BUILD",
			"properties" : 
			[
				{
					"name" : "HELPSTRING",
					"value" : "No help, variable specified on the command line."
				}
			],
			"type" : "UNINITIALIZED",
			"value" : "20230512"
		},
		{
			"name" : "MIRALL_VERSION_SUFFIX",
			"properties" : 
			[
				{
					"name" : "HELPSTRING",
					"value" : "No help, variable specified on the command line."
				}
			],
			"type" : "UNINITIALIZED",
			"value" : "daily-Win64"
		},
		{
			"name" : "MSVC_REDIST_DIR",
			"properties" : 
			[
				{
					"name" : "ADVANCED",
					"value" : "1"
				},
				{
					"name" : "HELPSTRING",
					"value" : "Path to a file."
				}
			],
			"type" : "PATH",
			"value" : "C:/Program Files (x86)/Microsoft Visual Studio/2019/Professional/VC/Redist/MSVC/14.29.30133"
		},
		{
			"name" : "NEXTCLOUD_BACKGROUND_COLOR",
			"properties" : 
			[
				{
					"name" : "HELPSTRING",
					"value" : "Default Nextcloud background color"
				}
			],
			"type" : "STRING",
			"value" : "#0082c9"
		},
		{
			"name" : "NO_MSG_HANDLER",
			"properties" : 
			[
				{
					"name" : "HELPSTRING",
					"value" : "Don't redirect QDebug outputs to the log window/file"
				}
			],
			"type" : "BOOL",
			"value" : "OFF"
		},
		{
			"name" : "NO_RENAME_EXTENSION",
			"properties" : 
			[
				{
					"name" : "HELPSTRING",
					"value" : "Do not issue rename if the extension changes"
				}
			],
			"type" : "BOOL",
			"value" : "0"
		},
		{
			"name" : "OPENSSL_APPLINK_SOURCE",
			"properties" : 
			[
				{
					"name" : "HELPSTRING",
					"value" : "Path to a file."
				}
			],
			"type" : "FILEPATH",
			"value" : "C:/OpenSSL/Win64/include/openssl/applink.c"
		},
		{
			"name" : "OPENSSL_INCLUDE_DIR",
			"properties" : 
			[
				{
					"name" : "ADVANCED",
					"value" : "1"
				},
				{
					"name" : "HELPSTRING",
					"value" : "Path to a file."
				}
			],
			"type" : "PATH",
			"value" : "C:/OpenSSL/Win64/include"
		},
		{
			"name" : "OPENSSL_LIBRARIES",
			"properties" : 
			[
				{
					"name" : "HELPSTRING",
					"value" : "No help, variable specified on the command line."
				}
			],
			"type" : "UNINITIALIZED",
			"value" : "c:/OpenSSL/Win64/lib"
		},
		{
			"name" : "OPENSSL_ROOT_DIR",
			"properties" : 
			[
				{
					"name" : "HELPSTRING",
					"value" : "No help, variable specified on the command line."
				}
			],
			"type" : "UNINITIALIZED",
			"value" : "c:/OpenSSL/Win64"
		},
		{
			"name" : "OWNCLOUD_5XX_NO_BLACKLIST",
			"properties" : 
			[
				{
					"name" : "HELPSTRING",
					"value" : "OWNCLOUD_5XX_NO_BLACKLIST"
				}
			],
			"type" : "BOOL",
			"value" : "OFF"
		},
		{
			"name" : "P4COMMAND",
			"properties" : 
			[
				{
					"name" : "ADVANCED",
					"value" : "1"
				},
				{
					"name" : "HELPSTRING",
					"value" : "(This variable does not exist and should not be used)"
				}
			],
			"type" : "UNINITIALIZED",
			"value" : ""
		},
		{
			"name" : "PDFLATEX_EXECUTABLE",
			"properties" : 
			[
				{
					"name" : "ADVANCED",
					"value" : "1"
				},
				{
					"name" : "HELPSTRING",
					"value" : "PDF LaTeX"
				}
			],
			"type" : "FILEPATH",
			"value" : "PDFLATEX_EXECUTABLE-NOTFOUND"
		},
		{
			"name" : "Png2Ico_EXECUTABLE",
			"properties" : 
			[
				{
					"name" : "ADVANCED",
					"value" : "1"
				},
				{
					"name" : "HELPSTRING",
					"value" : "Path to a program."
				}
			],
			"type" : "FILEPATH",
			"value" : "C:/NextCloud/tools/png2ico.exe"
		},
		{
			"name" : "QML_IMPORT_PATH",
			"properties" : 
			[
				{
					"name" : "HELPSTRING",
					"value" : ""
				}
			],
			"type" : "STRING",
			"value" : "C:/NextCloud/client-building/desktop/theme"
		},
		{
			"name" : "QT_CREATOR_SKIP_PACKAGE_MANAGER_SETUP",
			"properties" : 
			[
				{
					"name" : "HELPSTRING",
					"value" : "Skip Qt Creator's package manager auto-setup"
				}
			],
			"type" : "BOOL",
			"value" : "OFF"
		},
		{
			"name" : "QT_QMAKE_EXECUTABLE",
			"properties" : 
			[
				{
					"name" : "HELPSTRING",
					"value" : "No help, variable specified on the command line."
				}
			],
			"type" : "STRING",
			"value" : ""
		},
		{
			"name" : "QUICK_COMPILER",
			"properties" : 
			[
				{
					"name" : "HELPSTRING",
					"value" : "Use QtQuick compiler to improve performance"
				}
			],
			"type" : "BOOL",
			"value" : "OFF"
		},
		{
			"name" : "Qt5Concurrent_DIR",
			"properties" : 
			[
				{
					"name" : "HELPSTRING",
					"value" : "The directory containing a CMake configuration file for Qt5Concurrent."
				}
			],
			"type" : "PATH",
			"value" : "C:/Qt/5.15.8/msvc2019_64/lib/cmake/Qt5Concurrent"
		},
		{
			"name" : "Qt5Core_DIR",
			"properties" : 
			[
				{
					"name" : "HELPSTRING",
					"value" : "The directory containing a CMake configuration file for Qt5Core."
				}
			],
			"type" : "PATH",
			"value" : "C:/Qt/5.15.8/msvc2019_64/lib/cmake/Qt5Core"
		},
		{
			"name" : "Qt5Gui_DIR",
			"properties" : 
			[
				{
					"name" : "HELPSTRING",
					"value" : "The directory containing a CMake configuration file for Qt5Gui."
				}
			],
			"type" : "PATH",
			"value" : "C:/Qt/5.15.8/msvc2019_64/lib/cmake/Qt5Gui"
		},
		{
			"name" : "Qt5Keychain_DIR",
			"properties" : 
			[
				{
					"name" : "HELPSTRING",
					"value" : "The directory containing a CMake configuration file for Qt5Keychain."
				}
			],
			"type" : "PATH",
			"value" : "C:/NextCloud/client-building/QtKeychain/lib/cmake/Qt5Keychain"
		},
		{
			"name" : "Qt5LinguistTools_DIR",
			"properties" : 
			[
				{
					"name" : "HELPSTRING",
					"value" : "The directory containing a CMake configuration file for Qt5LinguistTools."
				}
			],
			"type" : "PATH",
			"value" : "C:/Qt/5.15.8/msvc2019_64/lib/cmake/Qt5LinguistTools"
		},
		{
			"name" : "Qt5Network_DIR",
			"properties" : 
			[
				{
					"name" : "HELPSTRING",
					"value" : "The directory containing a CMake configuration file for Qt5Network."
				}
			],
			"type" : "PATH",
			"value" : "C:/Qt/5.15.8/msvc2019_64/lib/cmake/Qt5Network"
		},
		{
			"name" : "Qt5Positioning_DIR",
			"properties" : 
			[
				{
					"name" : "HELPSTRING",
					"value" : "The directory containing a CMake configuration file for Qt5Positioning."
				}
			],
			"type" : "PATH",
			"value" : "C:/Qt/5.15.8/msvc2019_64/lib/cmake/Qt5Positioning"
		},
		{
			"name" : "Qt5PrintSupport_DIR",
			"properties" : 
			[
				{
					"name" : "HELPSTRING",
					"value" : "The directory containing a CMake configuration file for Qt5PrintSupport."
				}
			],
			"type" : "PATH",
			"value" : "C:/Qt/5.15.8/msvc2019_64/lib/cmake/Qt5PrintSupport"
		},
		{
			"name" : "Qt5QmlModels_DIR",
			"properties" : 
			[
				{
					"name" : "HELPSTRING",
					"value" : "The directory containing a CMake configuration file for Qt5QmlModels."
				}
			],
			"type" : "PATH",
			"value" : "C:/Qt/5.15.8/msvc2019_64/lib/cmake/Qt5QmlModels"
		},
		{
			"name" : "Qt5Qml_DIR",
			"properties" : 
			[
				{
					"name" : "HELPSTRING",
					"value" : "The directory containing a CMake configuration file for Qt5Qml."
				}
			],
			"type" : "PATH",
			"value" : "C:/Qt/5.15.8/msvc2019_64/lib/cmake/Qt5Qml"
		},
		{
			"name" : "Qt5QuickControls2_DIR",
			"properties" : 
			[
				{
					"name" : "HELPSTRING",
					"value" : "The directory containing a CMake configuration file for Qt5QuickControls2."
				}
			],
			"type" : "PATH",
			"value" : "C:/Qt/5.15.8/msvc2019_64/lib/cmake/Qt5QuickControls2"
		},
		{
			"name" : "Qt5Quick_DIR",
			"properties" : 
			[
				{
					"name" : "HELPSTRING",
					"value" : "The directory containing a CMake configuration file for Qt5Quick."
				}
			],
			"type" : "PATH",
			"value" : "C:/Qt/5.15.8/msvc2019_64/lib/cmake/Qt5Quick"
		},
		{
			"name" : "Qt5Svg_DIR",
			"properties" : 
			[
				{
					"name" : "HELPSTRING",
					"value" : "The directory containing a CMake configuration file for Qt5Svg."
				}
			],
			"type" : "PATH",
			"value" : "C:/Qt/5.15.8/msvc2019_64/lib/cmake/Qt5Svg"
		},
		{
			"name" : "Qt5Test_DIR",
			"properties" : 
			[
				{
					"name" : "HELPSTRING",
					"value" : "The directory containing a CMake configuration file for Qt5Test."
				}
			],
			"type" : "PATH",
			"value" : "C:/Qt/5.15.8/msvc2019_64/lib/cmake/Qt5Test"
		},
		{
			"name" : "Qt5WebChannel_DIR",
			"properties" : 
			[
				{
					"name" : "HELPSTRING",
					"value" : "The directory containing a CMake configuration file for Qt5WebChannel."
				}
			],
			"type" : "PATH",
			"value" : "C:/Qt/5.15.8/msvc2019_64/lib/cmake/Qt5WebChannel"
		},
		{
			"name" : "Qt5WebEngineCore_DIR",
			"properties" : 
			[
				{
					"name" : "HELPSTRING",
					"value" : "The directory containing a CMake configuration file for Qt5WebEngineCore."
				}
			],
			"type" : "PATH",
			"value" : "C:/Qt/5.15.8/msvc2019_64/lib/cmake/Qt5WebEngineCore"
		},
		{
			"name" : "Qt5WebEngineWidgets_DIR",
			"properties" : 
			[
				{
					"name" : "HELPSTRING",
					"value" : "The directory containing a CMake configuration file for Qt5WebEngineWidgets."
				}
			],
			"type" : "PATH",
			"value" : "C:/Qt/5.15.8/msvc2019_64/lib/cmake/Qt5WebEngineWidgets"
		},
		{
			"name" : "Qt5WebEngine_DIR",
			"properties" : 
			[
				{
					"name" : "HELPSTRING",
					"value" : "The directory containing a CMake configuration file for Qt5WebEngine."
				}
			],
			"type" : "PATH",
			"value" : "C:/Qt/5.15.8/msvc2019_64/lib/cmake/Qt5WebEngine"
		},
		{
			"name" : "Qt5WebSockets_DIR",
			"properties" : 
			[
				{
					"name" : "HELPSTRING",
					"value" : "The directory containing a CMake configuration file for Qt5WebSockets."
				}
			],
			"type" : "PATH",
			"value" : "C:/Qt/5.15.8/msvc2019_64/lib/cmake/Qt5WebSockets"
		},
		{
			"name" : "Qt5Widgets_DIR",
			"properties" : 
			[
				{
					"name" : "HELPSTRING",
					"value" : "The directory containing a CMake configuration file for Qt5Widgets."
				}
			],
			"type" : "PATH",
			"value" : "C:/Qt/5.15.8/msvc2019_64/lib/cmake/Qt5Widgets"
		},
		{
			"name" : "Qt5Xml_DIR",
			"properties" : 
			[
				{
					"name" : "HELPSTRING",
					"value" : "The directory containing a CMake configuration file for Qt5Xml."
				}
			],
			"type" : "PATH",
			"value" : "C:/Qt/5.15.8/msvc2019_64/lib/cmake/Qt5Xml"
		},
		{
			"name" : "Qt5_DIR",
			"properties" : 
			[
				{
					"name" : "HELPSTRING",
					"value" : "The directory containing a CMake configuration file for Qt5."
				}
			],
			"type" : "PATH",
			"value" : "C:/Qt/5.15.8/msvc2019_64/lib/cmake/Qt5"
		},
		{
			"name" : "SBIN_INSTALL_DIR",
			"properties" : 
			[
				{
					"name" : "HELPSTRING",
					"value" : "-"
				}
			],
			"type" : "PATH",
			"value" : "."
		},
		{
			"name" : "SHARE_INSTALL_PREFIX",
			"properties" : 
			[
				{
					"name" : "HELPSTRING",
					"value" : "-"
				}
			],
			"type" : "PATH",
			"value" : "share"
		},
		{
			"name" : "SITE",
			"properties" : 
			[
				{
					"name" : "ADVANCED",
					"value" : "1"
				},
				{
					"name" : "HELPSTRING",
					"value" : "Name of the computer/site where compile is being run"
				}
			],
			"type" : "STRING",
			"value" : "BE2BC629"
		},
		{
			"name" : "SOUND_INSTALL_DIR",
			"properties" : 
			[
				{
					"name" : "HELPSTRING",
					"value" : "-"
				}
			],
			"type" : "PATH",
			"value" : "."
		},
		{
			"name" : "SPHINX_EXECUTABLE",
			"properties" : 
			[
				{
					"name" : "ADVANCED",
					"value" : "1"
				},
				{
					"name" : "HELPSTRING",
					"value" : "Sphinx documentation generator"
				}
			],
			"type" : "FILEPATH",
			"value" : "SPHINX_EXECUTABLE-NOTFOUND"
		},
		{
			"name" : "SSL_EAY_DEBUG",
			"properties" : 
			[
				{
					"name" : "HELPSTRING",
					"value" : "Path to a library."
				}
			],
			"type" : "FILEPATH",
			"value" : "C:/OpenSSL/Win64/lib/VC/libssl64MDd.lib"
		},
		{
			"name" : "SSL_EAY_LIBRARY_DEBUG",
			"properties" : 
			[
				{
					"name" : "ADVANCED",
					"value" : "1"
				},
				{
					"name" : "HELPSTRING",
					"value" : "(This variable does not exist and should not be used)"
				}
			],
			"type" : "UNINITIALIZED",
			"value" : ""
		},
		{
			"name" : "SSL_EAY_LIBRARY_RELEASE",
			"properties" : 
			[
				{
					"name" : "ADVANCED",
					"value" : "1"
				},
				{
					"name" : "HELPSTRING",
					"value" : "(This variable does not exist and should not be used)"
				}
			],
			"type" : "UNINITIALIZED",
			"value" : ""
		},
		{
			"name" : "SSL_EAY_RELEASE",
			"properties" : 
			[
				{
					"name" : "HELPSTRING",
					"value" : "Path to a library."
				}
			],
			"type" : "FILEPATH",
			"value" : "C:/OpenSSL/Win64/lib/VC/libssl64MD.lib"
		},
		{
			"name" : "SVG_CONVERTER",
			"properties" : 
			[
				{
					"name" : "HELPSTRING",
					"value" : "Path to a program."
				}
			],
			"type" : "FILEPATH",
			"value" : "C:/Program Files/Inkscape/bin/inkscape.com"
		},
		{
			"name" : "SVNCOMMAND",
			"properties" : 
			[
				{
					"name" : "ADVANCED",
					"value" : "1"
				},
				{
					"name" : "HELPSTRING",
					"value" : "(This variable does not exist and should not be used)"
				}
			],
			"type" : "UNINITIALIZED",
			"value" : ""
		},
		{
			"name" : "SYSCONF_INSTALL_DIR",
			"properties" : 
			[
				{
					"name" : "HELPSTRING",
					"value" : "-"
				}
			],
			"type" : "PATH",
			"value" : "config"
		},
		{
			"name" : "TOKEN_AUTH_ONLY",
			"properties" : 
			[
				{
					"name" : "HELPSTRING",
					"value" : "TOKEN_AUTH_ONLY"
				}
			],
			"type" : "BOOL",
			"value" : "OFF"
		},
		{
			"name" : "WITH_CRASHREPORTER",
			"properties" : 
			[
				{
					"name" : "HELPSTRING",
					"value" : "Build crashreporter"
				}
			],
			"type" : "BOOL",
			"value" : "OFF"
		},
		{
			"name" : "WITH_PROVIDERS",
			"properties" : 
			[
				{
					"name" : "HELPSTRING",
					"value" : "Build with providers list"
				}
			],
			"type" : "BOOL",
			"value" : "ON"
		},
		{
			"name" : "ZLIB_INCLUDE_DIR",
			"properties" : 
			[
				{
					"name" : "ADVANCED",
					"value" : "1"
				},
				{
					"name" : "HELPSTRING",
					"value" : "Path to a file."
				}
			],
			"type" : "PATH",
			"value" : "C:/NextCloud/client-building/zlib"
		},
		{
			"name" : "ZLIB_LIBRARY",
			"properties" : 
			[
				{
					"name" : "HELPSTRING",
					"value" : "No help, variable specified on the command line."
				}
			],
			"type" : "UNINITIALIZED",
			"value" : "c:/Nextcloud/client-building/zlib/build/Release/zlibstatic.lib"
		},
		{
			"name" : "ZLIB_LIBRARY_DEBUG",
			"properties" : 
			[
				{
					"name" : "ADVANCED",
					"value" : "1"
				},
				{
					"name" : "HELPSTRING",
					"value" : "Path to a library."
				}
			],
			"type" : "FILEPATH",
			"value" : "ZLIB_LIBRARY_DEBUG-NOTFOUND"
		},
		{
			"name" : "ZLIB_LIBRARY_RELEASE",
			"properties" : 
			[
				{
					"name" : "ADVANCED",
					"value" : "1"
				},
				{
					"name" : "HELPSTRING",
					"value" : "Path to a library."
				}
			],
			"type" : "FILEPATH",
			"value" : "ZLIB_LIBRARY_RELEASE-NOTFOUND"
		},
		{
			"name" : "_GNUInstallDirs_LAST_CMAKE_INSTALL_PREFIX",
			"properties" : 
			[
				{
					"name" : "HELPSTRING",
					"value" : "CMAKE_INSTALL_PREFIX during last run"
				}
			],
			"type" : "INTERNAL",
			"value" : "C:/NextCloud/client-building/install/Release/Win64"
		},
		{
			"name" : "client_BINARY_DIR",
			"properties" : 
			[
				{
					"name" : "HELPSTRING",
					"value" : "Value Computed by CMake"
				}
			],
			"type" : "STATIC",
			"value" : "C:/NextCloud/client-building/desktop/build"
		},
		{
			"name" : "client_IS_TOP_LEVEL",
			"properties" : 
			[
				{
					"name" : "HELPSTRING",
					"value" : "Value Computed by CMake"
				}
			],
			"type" : "STATIC",
			"value" : "ON"
		},
		{
			"name" : "client_SOURCE_DIR",
			"properties" : 
			[
				{
					"name" : "HELPSTRING",
					"value" : "Value Computed by CMake"
				}
			],
			"type" : "STATIC",
			"value" : "C:/NextCloud/client-building/desktop"
		},
		{
			"name" : "cmd_BINARY_DIR",
			"properties" : 
			[
				{
					"name" : "HELPSTRING",
					"value" : "Value Computed by CMake"
				}
			],
			"type" : "STATIC",
			"value" : "C:/NextCloud/client-building/desktop/build/src/cmd"
		},
		{
			"name" : "cmd_IS_TOP_LEVEL",
			"properties" : 
			[
				{
					"name" : "HELPSTRING",
					"value" : "Value Computed by CMake"
				}
			],
			"type" : "STATIC",
			"value" : "OFF"
		},
		{
			"name" : "cmd_SOURCE_DIR",
			"properties" : 
			[
				{
					"name" : "HELPSTRING",
					"value" : "Value Computed by CMake"
				}
			],
			"type" : "STATIC",
			"value" : "C:/NextCloud/client-building/desktop/src/cmd"
		},
		{
			"name" : "gui_BINARY_DIR",
			"properties" : 
			[
				{
					"name" : "HELPSTRING",
					"value" : "Value Computed by CMake"
				}
			],
			"type" : "STATIC",
			"value" : "C:/NextCloud/client-building/desktop/build/src/gui"
		},
		{
			"name" : "gui_IS_TOP_LEVEL",
			"properties" : 
			[
				{
					"name" : "HELPSTRING",
					"value" : "Value Computed by CMake"
				}
			],
			"type" : "STATIC",
			"value" : "OFF"
		},
		{
			"name" : "gui_SOURCE_DIR",
			"properties" : 
			[
				{
					"name" : "HELPSTRING",
					"value" : "Value Computed by CMake"
				}
			],
			"type" : "STATIC",
			"value" : "C:/NextCloud/client-building/desktop/src/gui"
		},
		{
			"name" : "libcsync_BINARY_DIR",
			"properties" : 
			[
				{
					"name" : "HELPSTRING",
					"value" : "Value Computed by CMake"
				}
			],
			"type" : "STATIC",
			"value" : "C:/NextCloud/client-building/desktop/build/src/csync"
		},
		{
			"name" : "libcsync_IS_TOP_LEVEL",
			"properties" : 
			[
				{
					"name" : "HELPSTRING",
					"value" : "Value Computed by CMake"
				}
			],
			"type" : "STATIC",
			"value" : "OFF"
		},
		{
			"name" : "libcsync_SOURCE_DIR",
			"properties" : 
			[
				{
					"name" : "HELPSTRING",
					"value" : "Value Computed by CMake"
				}
			],
			"type" : "STATIC",
			"value" : "C:/NextCloud/client-building/desktop/src/csync"
		},
		{
			"name" : "libsync_BINARY_DIR",
			"properties" : 
			[
				{
					"name" : "HELPSTRING",
					"value" : "Value Computed by CMake"
				}
			],
			"type" : "STATIC",
			"value" : "C:/NextCloud/client-building/desktop/build/src/libsync"
		},
		{
			"name" : "libsync_IS_TOP_LEVEL",
			"properties" : 
			[
				{
					"name" : "HELPSTRING",
					"value" : "Value Computed by CMake"
				}
			],
			"type" : "STATIC",
			"value" : "OFF"
		},
		{
			"name" : "libsync_SOURCE_DIR",
			"properties" : 
			[
				{
					"name" : "HELPSTRING",
					"value" : "Value Computed by CMake"
				}
			],
			"type" : "STATIC",
			"value" : "C:/NextCloud/client-building/desktop/src/libsync"
		}
	],
	"kind" : "cache",
	"version" : 
	{
		"major" : 2,
		"minor" : 0
	}
}
